{
  "parts": [
    {
      "name": "Seat",
      "stock": 55,
      "alert": 20
    },
    {
      "name": "Back support",
      "stock": 55,
      "alert": 20
    },
    {
      "name": "Arm rest",
      "stock": 110,
      "alert": 40
    },
    {
      "name": "Wheels",
      "stock": 275,
      "alert": 50
    },
    {
      "name": "Wheel arm",
      "stock": 275,
      "alert": 50
    },
    {
      "name": "Center stand",
      "stock": 55,
      "alert": 20
    },
    {
      "name": "Bots",
      "stock": 1000,
      "alert": 100
    }
  ],
  "products": {
    "Chair": [
      {
        "part": "Arm rest",
        "qty": 2
      },
      {
        "part": "Back support",
        "qty": 1
      },
      {
        "part": "Bots",
        "qty": 20
      },
      {
        "part": "Center stand",
        "qty": 1
      },
      {
        "part": "Seat",
        "qty": 1
      },
      {
        "part": "Wheel arm",
        "qty": 5
      },
      {
        "part": "Wheels",
        "qty": 5
      }
    ]
  },
  "production_log": [
    {
      "product": "Chair",
      "qty": 20,
      "time": "2026-03-12 12:53 AM",
      "parts_used": [
        {
          "part": "Arm rest",
          "qty": 40
        },
        {
          "part": "Back support",
          "qty": 20
        },
        {
          "part": "Bots",
          "qty": 400
        },
        {
          "part": "Center stand",
          "qty": 20
        },
        {
          "part": "Seat",
          "qty": 20
        },
        {
          "part": "Wheel arm",
          "qty": 100
        },
        {
          "part": "Wheels",
          "qty": 100
        }
      ]
    },
    {
      "product": "Chair",
      "qty": 25,
      "time": "2026-03-12 12:56 AM",
      "parts_used": [
        {
          "part": "Arm rest",
          "qty": 50
        },
        {
          "part": "Back support",
          "qty": 25
        },
        {
          "part": "Bots",
          "qty": 500
        },
        {
          "part": "Center stand",
          "qty": 25
        },
        {
          "part": "Seat",
          "qty": 25
        },
        {
          "part": "Wheel arm",
          "qty": 125
        },
        {
          "part": "Wheels",
          "qty": 125
        }
      ]
    }
  ],
  "inventory_log": [
    {
      "Time": "2026-03-12 12:45 AM",
      "Part": "Seat",
      "Previous Stock": 0,
      "Change": 100,
      "New Stock": 100,
      "Reason": "Part Created"
    },
    {
      "Time": "2026-03-12 12:46 AM",
      "Part": "Seat",
      "Previous Stock": 0,
      "Change": 100,
      "New Stock": 100,
      "Reason": "Part Created"
    },
    {
      "Time": "2026-03-12 12:46 AM",
      "Part": "Back support",
      "Previous Stock": 0,
      "Change": 100,
      "New Stock": 100,
      "Reason": "Part Created"
    },
    {
      "Time": "2026-03-12 12:46 AM",
      "Part": "Arm rest",
      "Previous Stock": 0,
      "Change": 200,
      "New Stock": 200,
      "Reason": "Part Created"
    },
    {
      "Time": "2026-03-12 12:47 AM",
      "Part": "Wheels",
      "Previous Stock": 0,
      "Change": 500,
      "New Stock": 500,
      "Reason": "Part Created"
    },
    {
      "Time": "2026-03-12 12:47 AM",
      "Part": "Wheel arm",
      "Previous Stock": 0,
      "Change": 500,
      "New Stock": 500,
      "Reason": "Part Created"
    },
    {
      "Time": "2026-03-12 12:47 AM",
      "Part": "Center stand",
      "Previous Stock": 0,
      "Change": 100,
      "New Stock": 100,
      "Reason": "Part Created"
    },
    {
      "Time": "2026-03-12 12:47 AM",
      "Part": "Bots",
      "Previous Stock": 0,
      "Change": 1000,
      "New Stock": 1000,
      "Reason": "Part Created"
    },
    {
      "Time": "2026-03-12 12:53 AM",
      "Part": "Arm rest",
      "Previous Stock": 200,
      "Change": -40,
      "New Stock": 160,
      "Reason": "Production: Chair"
    },
    {
      "Time": "2026-03-12 12:53 AM",
      "Part": "Back support",
      "Previous Stock": 100,
      "Change": -20,
      "New Stock": 80,
      "Reason": "Production: Chair"
    },
    {
      "Time": "2026-03-12 12:53 AM",
      "Part": "Bots",
      "Previous Stock": 1000,
      "Change": -400,
      "New Stock": 600,
      "Reason": "Production: Chair"
    },
    {
      "Time": "2026-03-12 12:53 AM",
      "Part": "Center stand",
      "Previous Stock": 100,
      "Change": -20,
      "New Stock": 80,
      "Reason": "Production: Chair"
    },
    {
      "Time": "2026-03-12 12:53 AM",
      "Part": "Seat",
      "Previous Stock": 100,
      "Change": -20,
      "New Stock": 80,
      "Reason": "Production: Chair"
    },
    {
      "Time": "2026-03-12 12:53 AM",
      "Part": "Wheel arm",
      "Previous Stock": 500,
      "Change": -100,
      "New Stock": 400,
      "Reason": "Production: Chair"
    },
    {
      "Time": "2026-03-12 12:53 AM",
      "Part": "Wheels",
      "Previous Stock": 500,
      "Change": -100,
      "New Stock": 400,
      "Reason": "Production: Chair"
    },
    {
      "Time": "2026-03-12 12:56 AM",
      "Part": "Arm rest",
      "Previous Stock": 160,
      "Change": -50,
      "New Stock": 110,
      "Reason": "Production: Chair"
    },
    {
      "Time": "2026-03-12 12:56 AM",
      "Part": "Back support",
      "Previous Stock": 80,
      "Change": -25,
      "New Stock": 55,
      "Reason": "Production: Chair"
    },
    {
      "Time": "2026-03-12 12:56 AM",
      "Part": "Bots",
      "Previous Stock": 600,
      "Change": -500,
      "New Stock": 100,
      "Reason": "Production: Chair"
    },
    {
      "Time": "2026-03-12 12:56 AM",
      "Part": "Center stand",
      "Previous Stock": 80,
      "Change": -25,
      "New Stock": 55,
      "Reason": "Production: Chair"
    },
    {
      "Time": "2026-03-12 12:56 AM",
      "Part": "Seat",
      "Previous Stock": 80,
      "Change": -25,
      "New Stock": 55,
      "Reason": "Production: Chair"
    },
    {
      "Time": "2026-03-12 12:56 AM",
      "Part": "Wheel arm",
      "Previous Stock": 400,
      "Change": -125,
      "New Stock": 275,
      "Reason": "Production: Chair"
    },
    {
      "Time": "2026-03-12 12:56 AM",
      "Part": "Wheels",
      "Previous Stock": 400,
      "Change": -125,
      "New Stock": 275,
      "Reason": "Production: Chair"
    },
    {
      "Time": "2026-03-12 12:57 AM",
      "Part": "Bots",
      "Previous Stock": 100,
      "Change": 1500,
      "New Stock": 1600,
      "Reason": "Stock Added"
    },
    {
      "Time": "2026-03-12 12:59 AM",
      "Part": "Bots",
      "Previous Stock": 1600,
      "Change": -600,
      "New Stock": 1000,
      "Reason": "Manual Adjustment"
    }
  ]
}